rapidapi_axisdirect/__init__.py
rapidapi_axisdirect/__version__.py
rapidapi_axisdirect/exceptions.py
rapidapi_axisdirect/rapid_client.py
rapidapi_axisdirect/utils.py
rapidapi_axisdirect-0.0.2.dist-info/LICENSE
rapidapi_axisdirect-0.0.2.dist-info/METADATA
rapidapi_axisdirect-0.0.2.dist-info/WHEEL
rapidapi_axisdirect-0.0.2.dist-info/top_level.txt
rapidapi_axisdirect-0.0.2.dist-info/RECORD
